aerocae_robotics_controller-0.2.4.dist-info/licenses/LICENSE
arcpy/__init__.py
arcpy/arcpy.py
aerocae_robotics_controller-0.2.4.dist-info/METADATA
aerocae_robotics_controller-0.2.4.dist-info/WHEEL
aerocae_robotics_controller-0.2.4.dist-info/top_level.txt
aerocae_robotics_controller-0.2.4.dist-info/RECORD
