Metadata-Version: 2.4
Name: aerocae-robotics-controller
Version: 0.2.4
Summary: Python control interface for aerocae robotics
Author-email: Jiwei Wang <zmh78879@gmail.com>
Classifier: Programming Language :: Python :: 3
Classifier: License :: OSI Approved :: MIT License
Classifier: Operating System :: OS Independent
Requires-Python: >=3.8
License-File: LICENSE
Dynamic: license-file
